lekin/__init__.py
lekin/constraint/__init__.py
lekin/dashboard/__init__.py
lekin/dashboard/gantt.py
lekin/dashboard/pages.py
lekin/datasets/__init__.py
lekin/datasets/check_data.py
lekin/datasets/get_data.py
lekin/datasets/parse_data.py
lekin/lekin_struct/__init__.py
lekin/lekin_struct/allocation.py
lekin/lekin_struct/exceptions.py
lekin/lekin_struct/execution_mode.py
lekin/lekin_struct/job.py
lekin/lekin_struct/material.py
lekin/lekin_struct/operation.py
lekin/lekin_struct/relation.py
lekin/lekin_struct/resource.py
lekin/lekin_struct/route.py
lekin/lekin_struct/timeslot.py
lekin/objective/__init__.py
lekin/objective/makespan.py
lekin/objective/score.py
lekin/objective/tardiness.py
lekin/scheduler.py
lekin/solver/__init__.py
lekin/solver/config.py
lekin/solver/constraints/base.py
lekin/solver/construction_heuristics/__init__.py
lekin/solver/construction_heuristics/atcs.py
lekin/solver/construction_heuristics/backward.py
lekin/solver/construction_heuristics/base.py
lekin/solver/construction_heuristics/cr.py
lekin/solver/construction_heuristics/edd.py
lekin/solver/construction_heuristics/fifo.py
lekin/solver/construction_heuristics/forward.py
lekin/solver/construction_heuristics/lsf.py
lekin/solver/construction_heuristics/mix.py
lekin/solver/construction_heuristics/spt.py
lekin/solver/core/__init__.py
lekin/solver/core/base_solver.py
lekin/solver/core/ctp_solver.py
lekin/solver/core/problem.py
lekin/solver/core/solution.py
lekin/solver/meta_heuristics/__init__.py
lekin/solver/meta_heuristics/branch_and_bound.py
lekin/solver/meta_heuristics/critical_path.py
lekin/solver/meta_heuristics/encoding.py
lekin/solver/meta_heuristics/genetic.py
lekin/solver/meta_heuristics/hill_climbing.py
lekin/solver/meta_heuristics/nsga3.py
lekin/solver/meta_heuristics/pso.py
lekin/solver/meta_heuristics/shifting_bottle_neck.py
lekin/solver/meta_heuristics/tabu_search.py
lekin/solver/meta_heuristics/variable_neighborhood_search.py
lekin/solver/operation_research/__init__.py
lekin-0.0.2.dist-info/LICENSE
lekin-0.0.2.dist-info/METADATA
lekin-0.0.2.dist-info/WHEEL
lekin-0.0.2.dist-info/RECORD
